LICENSE.txt
MANIFEST.in
README.txt
requirements.txt.txt
setup.py
techai2/__init__.py
techai2.egg-info/PKG-INFO
techai2.egg-info/SOURCES.txt
techai2.egg-info/dependency_links.txt
techai2.egg-info/requires.txt
techai2.egg-info/top_level.txt