Metadata-Version: 2.1
Name: techai2
Version: 0.1.1
Summary: Neural Network Tool For Advanced And Big Neural Networks
Home-page: 
Author: Technik
Author-email: makemyclick3@gmail.com
License: MIT
Keywords: techai2 NeuralNetworks AI tool
Platform: UNKNOWN
Classifier: Development Status :: 5 - Production/Stable
Classifier: Intended Audience :: Education
Classifier: Operating System :: Microsoft :: Windows :: Windows 10
Classifier: License :: OSI Approved :: MIT License
Classifier: Programming Language :: Python :: 3
License-File: LICENSE.txt
